module2_package/__init__.py
module2_package/pandas_load.py
pandas_load-1.0.dist-info/METADATA
pandas_load-1.0.dist-info/WHEEL
pandas_load-1.0.dist-info/top_level.txt
pandas_load-1.0.dist-info/RECORD
