Metadata-Version: 2.4
Name: pandas_load
Version: 1.0
Summary: Basic package for loading and describing a given .csv data set
Home-page: https://github.com/JordanWilson0312/pythonsoftengmodule2
Author: Jordan Wilson
Author-email: 11037101@uvu.edu
Dynamic: author
Dynamic: author-email
Dynamic: home-page
Dynamic: summary
